envs/__init__.py
envs/__init__.pyc
envs/cli.py
envs/cli.pyc
envs/exceptions.py
envs/exceptions.pyc
envs/test_settings.py
envs/tests.py
envs/tests.pyc
envs/util.py
envs/util.pyc
envs/__pycache__/__init__.cpython-35.pyc
envs/__pycache__/__init__.cpython-36.pyc
envs/__pycache__/cli.cpython-36.pyc
envs/__pycache__/exceptions.cpython-35.pyc
envs/__pycache__/exceptions.cpython-36.pyc
envs/__pycache__/test_settings.cpython-35.pyc
envs/__pycache__/test_settings.cpython-36.pyc
envs/__pycache__/tests.cpython-35.pyc
envs/__pycache__/tests.cpython-36.pyc
envs/__pycache__/util.cpython-35.pyc
envs/__pycache__/util.cpython-36.pyc
envs/templates/settings.jinja2
envs-1.2.6.dist-info/METADATA
envs-1.2.6.dist-info/RECORD
envs-1.2.6.dist-info/WHEEL
envs-1.2.6.dist-info/entry_points.txt
envs-1.2.6.dist-info/top_level.txt
envs-1.2.6.dist-info/zip-safe
